amap_api_mcp/__init__.py
amap_api_mcp/server.py
amap_api_mcp_goki-0.1.2.dist-info/METADATA
amap_api_mcp_goki-0.1.2.dist-info/WHEEL
amap_api_mcp_goki-0.1.2.dist-info/entry_points.txt
amap_api_mcp_goki-0.1.2.dist-info/licenses/LICENSE
amap_api_mcp_goki-0.1.2.dist-info/RECORD
