Metadata-Version: 2.4
Name: amap-api-mcp-goki
Version: 0.1.2
Summary: MCP server for Amap (高德地图) API integration
Project-URL: Homepage, https://github.com/yourusername/amap-api-mcp
Project-URL: Repository, https://github.com/yourusername/amap-api-mcp.git
Project-URL: Issues, https://github.com/yourusername/amap-api-mcp/issues
Author-email: goki <654051206@qq.com>
License: MIT
License-File: LICENSE
Classifier: Development Status :: 3 - Alpha
Classifier: Intended Audience :: Developers
Classifier: License :: OSI Approved :: MIT License
Classifier: Programming Language :: Python :: 3
Classifier: Programming Language :: Python :: 3.8
Classifier: Programming Language :: Python :: 3.9
Classifier: Programming Language :: Python :: 3.10
Classifier: Programming Language :: Python :: 3.11
Classifier: Programming Language :: Python :: 3.12
Requires-Python: >=3.12
Requires-Dist: mcp>=1.0.0
Requires-Dist: pydantic>=2.0.0
Requires-Dist: python-dotenv>=0.19.0
Requires-Dist: requests>=2.25.0
Provides-Extra: dev
Requires-Dist: black; extra == 'dev'
Requires-Dist: flake8; extra == 'dev'
Requires-Dist: isort; extra == 'dev'
Requires-Dist: pytest>=6.0; extra == 'dev'
